adsToolBox/__init__.py
adsToolBox/cdc.py
adsToolBox/data_comparator.py
adsToolBox/data_factory.py
adsToolBox/db_mssql.py
adsToolBox/db_mysql.py
adsToolBox/db_pgsql.py
adsToolBox/ddl_operations.py
adsToolBox/dml_generator.py
adsToolBox/file_handler.py
adsToolBox/git_handler.py
adsToolBox/global_config.py
adsToolBox/google_calendar.py
adsToolBox/load_env.py
adsToolBox/logger.py
adsToolBox/mail_reader.py
adsToolBox/odoo.py
adsToolBox/pipeline.py
adsToolBox/timer.py
adsToolBox/to_sort/email.py
adsToolBox/to_sort/env.py
adstoolbox-2026.1.16.dist-info/METADATA
adstoolbox-2026.1.16.dist-info/WHEEL
adstoolbox-2026.1.16.dist-info/RECORD
